edc_pdutils/__init__.py
edc_pdutils/actions.py
edc_pdutils/admin_site.py
edc_pdutils/apps.py
edc_pdutils/choices.py
edc_pdutils/constants.py
edc_pdutils/database.py
edc_pdutils/helper.py
edc_pdutils/mappings.py
edc_pdutils/models.py
edc_pdutils/site.py
edc_pdutils/site_values_mappings.py
edc_pdutils/urls.py
edc_pdutils/column_handlers/__init__.py
edc_pdutils/column_handlers/column_apply.py
edc_pdutils/column_handlers/column_map.py
edc_pdutils/dataframes/__init__.py
edc_pdutils/dataframes/get_appointments.py
edc_pdutils/dataframes/get_crf.py
edc_pdutils/dataframes/get_eos.py
edc_pdutils/dataframes/get_next_appointments.py
edc_pdutils/dataframes/get_subject_consent.py
edc_pdutils/dataframes/get_subject_visit.py
edc_pdutils/df_exporters/__init__.py
edc_pdutils/df_exporters/csv_crf_inline_tables_exporter.py
edc_pdutils/df_exporters/csv_crf_tables_exporter.py
edc_pdutils/df_exporters/csv_exporter.py
edc_pdutils/df_exporters/csv_model_exporter.py
edc_pdutils/df_exporters/csv_noncrf_tables_exporter.py
edc_pdutils/df_exporters/tables_exporter.py
edc_pdutils/df_handlers/__init__.py
edc_pdutils/df_handlers/crf_df_handler.py
edc_pdutils/df_handlers/df_handler.py
edc_pdutils/df_handlers/non_crf_df_handler.py
edc_pdutils/df_handlers/registered_subject_df_handler.py
edc_pdutils/dialects/__init__.py
edc_pdutils/dialects/crf_dialect.py
edc_pdutils/dialects/mysql_dialect.py
edc_pdutils/dialects/rs_dialect.py
edc_pdutils/management/__init__.py
edc_pdutils/management/commands/__init__.py
edc_pdutils/management/commands/export_models.py
edc_pdutils/migrations/0001_initial.py
edc_pdutils/migrations/0002_auto_20180921_2242.py
edc_pdutils/migrations/__init__.py
edc_pdutils/table_to_dataframe/__init__.py
edc_pdutils/table_to_dataframe/helper.py
edc_pdutils/table_to_dataframe/table_to_dataframe.py
edc_pdutils/tables/__init__.py
edc_pdutils/tables/aliquot.py
edc_pdutils/tables/consent.py
edc_pdutils/tables/crf.py
edc_pdutils/tables/requisition.py
edc_pdutils/tables/table.py
edc_pdutils-1.0.2.dist-info/licenses/AUTHORS.rst
edc_pdutils-1.0.2.dist-info/licenses/LICENSE
edc_pdutils-1.0.2.dist-info/METADATA
edc_pdutils-1.0.2.dist-info/WHEEL
edc_pdutils-1.0.2.dist-info/top_level.txt
edc_pdutils-1.0.2.dist-info/RECORD
